_avif.pypy-73.so
avif-0.5.0.dist-info/COPYING
avif-0.5.0.dist-info/METADATA
avif-0.5.0.dist-info/top_level.txt
avif-0.5.0.dist-info/WHEEL
avif-0.5.0.dist-info/RECORD
avif.libs/libavif-a49840c3.so.9.0.0
avif/_build.py
avif/_api.py
avif/__init__.py
avif/tests/test_avif.py
avif/tests/__init__.py
avif/pillow/__init__.py
