Metadata-Version: 2.1
Name: avif
Version: 0.5.0
Summary: Python bindings for libavif
Home-page: https://github.com/Julian/avif
Author: Julian Berman
Author-email: Julian+avif@GrayVines.com
License: UNKNOWN
Project-URL: Source, https://github.com/Julian/avif
Project-URL: Issues, https://github.com/Julian/avif/issues/
Platform: UNKNOWN
Classifier: Development Status :: 3 - Alpha
Classifier: Operating System :: OS Independent
Classifier: Programming Language :: Python
Classifier: License :: OSI Approved :: MIT License
Classifier: Programming Language :: Python :: 3.7
Classifier: Programming Language :: Python :: 3.8
Classifier: Programming Language :: Python :: 3.9
Classifier: Programming Language :: Python :: 3
Classifier: Programming Language :: Python :: Implementation :: CPython
Classifier: Programming Language :: Python :: Implementation :: PyPy
Provides-Extra: pillow
